Metadata-Version: 1.0
Name: easysql2pd
Version: 0.0.2.4
Summary: sql for pandas
Home-page: https://github.com/StevenSunnySun/JT
Author: SSS
Author-email: steven_sunny_316@163.com
License: GPL Licence
Keywords: pip,sql,pandas,pd
Platform: any python3
